odoo/addons/mrp_production_filter_lot/README.rst
odoo/addons/mrp_production_filter_lot/__init__.py
odoo/addons/mrp_production_filter_lot/__manifest__.py
odoo/addons/mrp_production_filter_lot/i18n/it.po
odoo/addons/mrp_production_filter_lot/i18n/mrp_production_filter_lot.pot
odoo/addons/mrp_production_filter_lot/readme/CONTRIBUTORS.rst
odoo/addons/mrp_production_filter_lot/readme/DESCRIPTION.rst
odoo/addons/mrp_production_filter_lot/readme/USAGE.rst
odoo/addons/mrp_production_filter_lot/static/description/icon.png
odoo/addons/mrp_production_filter_lot/static/description/index.html
odoo/addons/mrp_production_filter_lot/wizards/__init__.py
odoo/addons/mrp_production_filter_lot/wizards/mrp_product_produce_line.py
odoo/addons/mrp_production_filter_lot/wizards/mrp_product_produce_views.xml
odoo12_addon_mrp_production_filter_lot-12.0.1.0.1.dist-info/METADATA
odoo12_addon_mrp_production_filter_lot-12.0.1.0.1.dist-info/WHEEL
odoo12_addon_mrp_production_filter_lot-12.0.1.0.1.dist-info/top_level.txt
odoo12_addon_mrp_production_filter_lot-12.0.1.0.1.dist-info/RECORD
