Metadata-Version: 2.1
Name: odoo12-addon-mrp-production-filter-lot
Version: 12.0.1.0.1
Summary: In production order production popup, filter lots based on their location and availability
Home-page: https://github.com/OCA/manufacture12.0/mrp_production_filter_lot
Author: Takobi, Odoo Community Association (OCA)
Author-email: support@odoo-community.org
License: AGPL-3
Platform: UNKNOWN
Classifier: Programming Language :: Python
Classifier: Framework :: Odoo
Classifier: Framework :: Odoo :: 12.0
Classifier: License :: OSI Approved :: GNU Affero General Public License v3
Requires-Python: >=3.5
Requires-Dist: odoo12-addon-stock-picking-filter-lot
Requires-Dist: odoo (<12.1dev,>=12.0a)
